moopy/__init__.py
moopy/_solve.py
moopy/core.py
moopy/scalarization.py
moopy/show_results.py
moopy/test.py
moopy/test_cases.py
moopy-0.0.5.dist-info/LICENSE
moopy-0.0.5.dist-info/METADATA
moopy-0.0.5.dist-info/WHEEL
moopy-0.0.5.dist-info/top_level.txt
moopy-0.0.5.dist-info/RECORD
