Metadata-Version: 2.1
Name: moopy
Version: 0.0.5
Summary: A package for Multi-Objective Optimization tools
Home-page: https://github.com/moo4all/MooPy.git
Author: Derk Kappelle
Author-email: 20672345+dkappelle@users.noreply.github.com
License: UNKNOWN
Platform: UNKNOWN
Classifier: Programming Language :: Python :: 3.7
Classifier: License :: OSI Approved :: GNU General Public License v3 (GPLv3)
